multiverse_parser/__init__.py
multiverse_parser/exporter/__init__.py
multiverse_parser/exporter/mjcf_exporter.py
multiverse_parser/exporter/urdf_exporter.py
multiverse_parser/factory/__init__.py
multiverse_parser/factory/body_builder.py
multiverse_parser/factory/factory.py
multiverse_parser/factory/geom_builder.py
multiverse_parser/factory/joint_builder.py
multiverse_parser/factory/material_builder.py
multiverse_parser/factory/mesh_builder.py
multiverse_parser/factory/points_builder.py
multiverse_parser/factory/texture_builder.py
multiverse_parser/factory/world_builder.py
multiverse_parser/importer/__init__.py
multiverse_parser/importer/mjcf_importer.py
multiverse_parser/importer/urdf_importer.py
multiverse_parser/importer/usd_importer.py
multiverse_parser/utils/__init__.py
multiverse_parser/utils/boxify.py
multiverse_parser/utils/mesh_exporter.py
multiverse_parser/utils/mesh_importer.py
multiverse_parser/utils/utils.py
multiverse_parser-0.0.2.dist-info/licenses/LICENSE
multiverse_parser-0.0.2.dist-info/METADATA
multiverse_parser-0.0.2.dist-info/WHEEL
multiverse_parser-0.0.2.dist-info/top_level.txt
multiverse_parser-0.0.2.dist-info/RECORD
