Metadata-Version: 2.4
Name: multiverse_parser
Version: 0.0.2
Summary: A parser that converts between different scene descriptions
Author-email: Giang Nguyen <hoanggia@uni-bremen.de>
License-Expression: MIT
Project-URL: Homepage, https://github.com/Multiverse-Framework/Multiverse
Project-URL: Bug Tracker, https://github.com/Multiverse-Framework/Multiverse-Parser/issues
Classifier: Programming Language :: Python :: 3
Classifier: Operating System :: OS Independent
Requires-Python: >=3.10
License-File: LICENSE
Requires-Dist: numpy
Requires-Dist: Pillow
Requires-Dist: scipy
Requires-Dist: urdf-parser-py
Requires-Dist: rospkg
Requires-Dist: mujoco
Dynamic: license-file
